commutation/__init__.py
commutation/commutatoralgebra.py
commutation/expression.py
commutation/style.py
commutation-1.5.0.dist-info/licenses/LICENSE
commutation-1.5.0.dist-info/METADATA
commutation-1.5.0.dist-info/WHEEL
commutation-1.5.0.dist-info/top_level.txt
commutation-1.5.0.dist-info/RECORD
