Metadata-Version: 2.4
Name: Commutation
Version: 1.5.0
Summary: A small package for doing commutator algebra
Author-email: Alaric Sanders <thathatatt@gmail.com>
Project-URL: Homepage, https://github.com/Spuriosity1/Commutation
Project-URL: Issues, https://github.com/Spuriosity1/Commutation/issues
Classifier: Programming Language :: Python :: 3
Classifier: License :: OSI Approved :: MIT License
Classifier: Operating System :: OS Independent
Requires-Python: >=3.8
License-File: LICENSE
Requires-Dist: ipython
Dynamic: license-file
